all_tools_on_blockchain/__init__.py
all_tools_on_blockchain/argparse.py
all_tools_on_blockchain/read.py
all_tools_on_blockchain-0.0.1.dist-info/METADATA
all_tools_on_blockchain-0.0.1.dist-info/WHEEL
all_tools_on_blockchain-0.0.1.dist-info/entry_points.txt
all_tools_on_blockchain-0.0.1.dist-info/top_level.txt
all_tools_on_blockchain-0.0.1.dist-info/RECORD
