Metadata-Version: 2.1
Name: all-tools-on-blockchain
Version: 0.0.1
Summary: All-in-one toolset for blockchain.
Home-page: https://shawnxu.me
Author: th35tr0n9
Author-email: shawn@hxzy.me
License: UNKNOWN
Platform: UNKNOWN
Requires-Dist: requests
Requires-Dist: prettytable
Requires-Dist: web3 >=6.0.0
